imgpatch/__init__.py
imgpatch-1.0.dist-info/LICENSE.txt
imgpatch-1.0.dist-info/METADATA
imgpatch-1.0.dist-info/WHEEL
imgpatch-1.0.dist-info/top_level.txt
imgpatch-1.0.dist-info/RECORD
